<?xml version="0.25" encoding="utf-8"?>
<TextureAtlas imagePath="Hog.png">
	<!-- Created with Adobe Animate version 22.0.3.179 -->
	<!-- http://www.adobe.com/products/animate.html -->
	<SubTexture name="Getfucked0000" x="0" y="0" width="60" height="82" frameX="-34" frameY="-56" frameWidth="160.5" frameHeight="142.25"/>
	<SubTexture name="Getfucked0001" x="60" y="0" width="60" height="82.75" frameX="-34" frameY="-55.75" frameWidth="160.5" frameHeight="142.25"/>
	<SubTexture name="Getfucked0002" x="120" y="0" width="58.75" height="83.5" frameX="-34" frameY="-55.5" frameWidth="160.5" frameHeight="142.25"/>
	<SubTexture name="Getfucked0003" x="178.75" y="0" width="58.25" height="85.75" frameX="-33.75" frameY="-53" frameWidth="160.5" frameHeight="142.25"/>
	<SubTexture name="Getfucked0004" x="237" y="0" width="59.75" height="86" frameX="-33.5" frameY="-52" frameWidth="160.5" frameHeight="142.25"/>
	<SubTexture name="Getfucked0005" x="296.75" y="0" width="65" height="86.5" frameX="-32.25" frameY="-51.5" frameWidth="160.5" frameHeight="142.25"/>
	<SubTexture name="Getfucked0006" x="361.75" y="0" width="77" height="86.75" frameX="-32.25" frameY="-51.25" frameWidth="160.5" frameHeight="142.25"/>
	<SubTexture name="Getfucked0007" x="438.75" y="0" width="79.5" height="81" frameX="-33.5" frameY="-57.25" frameWidth="160.5" frameHeight="142.25"/>
	<SubTexture name="Getfucked0008" x="518.25" y="0" width="71" height="77.75" frameX="-34" frameY="-60.25" frameWidth="160.5" frameHeight="142.25"/>
	<SubTexture name="Getfucked0009" x="589.25" y="0" width="67.75" height="77.75" frameX="-28" frameY="-60.25" frameWidth="160.5" frameHeight="142.25"/>
	<SubTexture name="Getfucked0010" x="657" y="0" width="75.75" height="78.5" frameX="-20.5" frameY="-59.5" frameWidth="160.5" frameHeight="142.25"/>
	<SubTexture name="Getfucked0011" x="732.75" y="0" width="75.5" height="78.75" frameX="-20.5" frameY="-59.25" frameWidth="160.5" frameHeight="142.25"/>
	<SubTexture name="Getfucked0012" x="808.25" y="0" width="75.5" height="78.75" frameX="-20.5" frameY="-59.25" frameWidth="160.5" frameHeight="142.25"/>
	<SubTexture name="Getfucked0013" x="883.75" y="0" width="75.5" height="78.75" frameX="-20.5" frameY="-59.25" frameWidth="160.5" frameHeight="142.25"/>
	<SubTexture name="Getfucked0014" x="883.75" y="0" width="75.5" height="78.75" frameX="-20.5" frameY="-59.25" frameWidth="160.5" frameHeight="142.25"/>
	<SubTexture name="Getfucked0015" x="883.75" y="0" width="75.5" height="78.75" frameX="-20.5" frameY="-59.25" frameWidth="160.5" frameHeight="142.25"/>
	<SubTexture name="Getfucked0016" x="883.75" y="0" width="75.5" height="78.75" frameX="-20.5" frameY="-59.25" frameWidth="160.5" frameHeight="142.25"/>
	<SubTexture name="Getfucked0017" x="883.75" y="0" width="75.5" height="78.75" frameX="-20.5" frameY="-59.25" frameWidth="160.5" frameHeight="142.25"/>
	<SubTexture name="Getfucked0018" x="883.75" y="0" width="75.5" height="78.75" frameX="-20.5" frameY="-59.25" frameWidth="160.5" frameHeight="142.25"/>
	<SubTexture name="Getfucked0019" x="883.75" y="0" width="75.5" height="78.75" frameX="-20.5" frameY="-59.25" frameWidth="160.5" frameHeight="142.25"/>
	<SubTexture name="Getfucked0020" x="0" y="86.75" width="84.75" height="50.25" frameX="-11" frameY="-84.5" frameWidth="160.5" frameHeight="142.25"/>
	<SubTexture name="Getfucked0021" x="84.75" y="86.75" width="85.25" height="50.25" frameX="-12" frameY="-84.5" frameWidth="160.5" frameHeight="142.25"/>
	<SubTexture name="Getfucked0022" x="170" y="86.75" width="93.75" height="47.25" frameX="-14.5" frameY="-87.5" frameWidth="160.5" frameHeight="142.25"/>
	<SubTexture name="Getfucked0023" x="263.75" y="86.75" width="93" height="45.75" frameX="-13.5" frameY="-89" frameWidth="160.5" frameHeight="142.25"/>
	<SubTexture name="Getfucked0024" x="356.75" y="86.75" width="90" height="44.25" frameX="-13.75" frameY="-90.5" frameWidth="160.5" frameHeight="142.25"/>
	<SubTexture name="Getfucked0025" x="446.75" y="86.75" width="76.25" height="46" frameX="0" frameY="-88.75" frameWidth="160.5" frameHeight="142.25"/>
	<SubTexture name="Getfucked0026" x="523" y="86.75" width="67.75" height="50" frameX="-8.5" frameY="-84.75" frameWidth="160.5" frameHeight="142.25"/>
	<SubTexture name="Getfucked0027" x="590.75" y="86.75" width="66.5" height="55.75" frameX="-11.25" frameY="-79.25" frameWidth="160.5" frameHeight="142.25"/>
	<SubTexture name="Getfucked0028" x="657.25" y="86.75" width="70.25" height="52.75" frameX="-8" frameY="-82.25" frameWidth="160.5" frameHeight="142.25"/>
	<SubTexture name="Getfucked0029" x="727.5" y="86.75" width="49.25" height="53.5" frameX="-46.25" frameY="-49" frameWidth="160.5" frameHeight="142.25"/>
	<SubTexture name="Getfucked0030" x="776.75" y="86.75" width="86.25" height="75.25" frameX="-31.5" frameY="-28.25" frameWidth="160.5" frameHeight="142.25"/>
	<SubTexture name="Getfucked0031" x="863" y="86.75" width="90" height="83.75" frameX="-27.75" frameY="-17.25" frameWidth="160.5" frameHeight="142.25"/>
	<SubTexture name="Getfucked0032" x="0" y="170.5" width="80" height="87.25" frameX="-28" frameY="-2" frameWidth="160.5" frameHeight="142.25"/>
	<SubTexture name="Getfucked0033" x="80" y="170.5" width="82" height="84.25" frameX="-27.75" frameY="-0.25" frameWidth="160.5" frameHeight="142.25"/>
	<SubTexture name="Getfucked0034" x="162" y="170.5" width="84.75" height="82" frameX="-28.25" frameY="0" frameWidth="160.5" frameHeight="142.25"/>
	<SubTexture name="Getfucked0035" x="246.75" y="170.5" width="108.5" height="66.5" frameX="-13.25" frameY="-6" frameWidth="160.5" frameHeight="142.25"/>
	<SubTexture name="Getfucked0036" x="355.25" y="170.5" width="128.5" height="48" frameX="-29" frameY="-34.75" frameWidth="160.5" frameHeight="142.25"/>
	<SubTexture name="Getfucked0037" x="483.75" y="170.5" width="68.5" height="50.75" frameX="-90.5" frameY="-41.5" frameWidth="160.5" frameHeight="142.25"/>
	<SubTexture name="Getfucked0038" x="552.25" y="170.5" width="106" height="56.75" frameX="-54.5" frameY="-36.75" frameWidth="160.5" frameHeight="142.25"/>
	<SubTexture name="Getfucked0039" x="658.25" y="170.5" width="147" height="98" frameX="-5.5" frameY="-43.25" frameWidth="160.5" frameHeight="142.25"/>
	<SubTexture name="Getfucked0040" x="805.25" y="170.5" width="68.75" height="88.75" frameX="-18.25" frameY="-52.5" frameWidth="160.5" frameHeight="142.25"/>
	<SubTexture name="Getfucked0041" x="874" y="170.5" width="74.25" height="52.25" frameX="-13.75" frameY="-88.75" frameWidth="160.5" frameHeight="142.25"/>
	<SubTexture name="Getfucked0042" x="948.25" y="170.5" width="63.75" height="38.75" frameX="-17" frameY="-103.5" frameWidth="160.5" frameHeight="142.25"/>
	<SubTexture name="HogDown0000" x="0" y="268.5" width="84.5" height="73.25" frameX="-5.75" frameY="-3.75" frameWidth="90.5" frameHeight="77.5"/>
	<SubTexture name="HogDown0001" x="84.5" y="268.5" width="87" height="76.5" frameX="-3.5" frameY="-0.75" frameWidth="90.5" frameHeight="77.5"/>
	<SubTexture name="HogDown0002" x="171.5" y="268.5" width="90.5" height="77" frameX="0" frameY="-0.5" frameWidth="90.5" frameHeight="77.5"/>
	<SubTexture name="HogDown0003" x="262" y="268.5" width="89.25" height="77.5" frameX="-0.25" frameY="0" frameWidth="90.5" frameHeight="77.5"/>
	<SubTexture name="HogDown0004" x="351.25" y="268.5" width="89.25" height="77.5" frameX="-0.25" frameY="0" frameWidth="90.5" frameHeight="77.5"/>
	<SubTexture name="HogDown0005" x="262" y="268.5" width="89.25" height="77.5" frameX="-0.25" frameY="0" frameWidth="90.5" frameHeight="77.5"/>
	<SubTexture name="HogDown0006" x="351.25" y="268.5" width="89.25" height="77.5" frameX="-0.25" frameY="0" frameWidth="90.5" frameHeight="77.5"/>
	<SubTexture name="HogDown0007" x="262" y="268.5" width="89.25" height="77.5" frameX="-0.25" frameY="0" frameWidth="90.5" frameHeight="77.5"/>
	<SubTexture name="HogDown0008" x="351.25" y="268.5" width="89.25" height="77.5" frameX="-0.25" frameY="0" frameWidth="90.5" frameHeight="77.5"/>
	<SubTexture name="HogDown0009" x="262" y="268.5" width="89.25" height="77.5" frameX="-0.25" frameY="0" frameWidth="90.5" frameHeight="77.5"/>
	<SubTexture name="HogIdle0000" x="440.5" y="268.5" width="64" height="86" frameX="-0.5" frameY="-2" frameWidth="64.75" frameHeight="88"/>
	<SubTexture name="HogIdle0001" x="504.5" y="268.5" width="64" height="85.75" frameX="-0.5" frameY="-2" frameWidth="64.75" frameHeight="88"/>
	<SubTexture name="HogIdle0002" x="568.5" y="268.5" width="64.25" height="86.25" frameX="-0.5" frameY="-1.75" frameWidth="64.75" frameHeight="88"/>
	<SubTexture name="HogIdle0003" x="632.75" y="268.5" width="64.25" height="86" frameX="-0.5" frameY="-1.75" frameWidth="64.75" frameHeight="88"/>
	<SubTexture name="HogIdle0004" x="697" y="268.5" width="64" height="87.5" frameX="-0.75" frameY="-0.5" frameWidth="64.75" frameHeight="88"/>
	<SubTexture name="HogIdle0005" x="761" y="268.5" width="64" height="87.25" frameX="-0.75" frameY="-0.5" frameWidth="64.75" frameHeight="88"/>
	<SubTexture name="HogIdle0006" x="825" y="268.5" width="64.5" height="88" frameX="0" frameY="0" frameWidth="64.75" frameHeight="88"/>
	<SubTexture name="HogIdle0007" x="889.5" y="268.5" width="64.5" height="87.5" frameX="0" frameY="-0.25" frameWidth="64.75" frameHeight="88"/>
	<SubTexture name="HogIdle0008" x="954" y="268.5" width="64.5" height="87.75" frameX="0" frameY="-0.25" frameWidth="64.75" frameHeight="88"/>
	<SubTexture name="HogIdle0009" x="0" y="356.5" width="64.5" height="87.5" frameX="0" frameY="-0.25" frameWidth="64.75" frameHeight="88"/>
	<SubTexture name="HogIdle0010" x="954" y="268.5" width="64.5" height="87.75" frameX="0" frameY="-0.25" frameWidth="64.75" frameHeight="88"/>
	<SubTexture name="HogIdle0011" x="0" y="356.5" width="64.5" height="87.5" frameX="0" frameY="-0.25" frameWidth="64.75" frameHeight="88"/>
	<SubTexture name="HogIdle0012" x="954" y="268.5" width="64.5" height="87.75" frameX="0" frameY="-0.25" frameWidth="64.75" frameHeight="88"/>
	<SubTexture name="HogIdle0013" x="0" y="356.5" width="64.5" height="87.5" frameX="0" frameY="-0.25" frameWidth="64.75" frameHeight="88"/>
	<SubTexture name="HogLeft0000" x="64.5" y="356.5" width="76" height="86" frameX="0" frameY="0" frameWidth="79" frameHeight="86"/>
	<SubTexture name="HogLeft0001" x="140.5" y="356.5" width="74.5" height="85.5" frameX="-3.5" frameY="-0.5" frameWidth="79" frameHeight="86"/>
	<SubTexture name="HogLeft0002" x="215" y="356.5" width="74.25" height="85.5" frameX="-4.75" frameY="-0.5" frameWidth="79" frameHeight="86"/>
	<SubTexture name="HogLeft0003" x="289.25" y="356.5" width="73.75" height="85.5" frameX="-5.25" frameY="-0.5" frameWidth="79" frameHeight="86"/>
	<SubTexture name="HogLeft0004" x="363" y="356.5" width="73.5" height="85.75" frameX="-5.25" frameY="-0.25" frameWidth="79" frameHeight="86"/>
	<SubTexture name="HogLeft0005" x="289.25" y="356.5" width="73.75" height="85.5" frameX="-5.25" frameY="-0.5" frameWidth="79" frameHeight="86"/>
	<SubTexture name="HogLeft0006" x="363" y="356.5" width="73.5" height="85.75" frameX="-5.25" frameY="-0.25" frameWidth="79" frameHeight="86"/>
	<SubTexture name="HogLeft0007" x="289.25" y="356.5" width="73.75" height="85.5" frameX="-5.25" frameY="-0.5" frameWidth="79" frameHeight="86"/>
	<SubTexture name="HogLeft0008" x="363" y="356.5" width="73.5" height="85.75" frameX="-5.25" frameY="-0.25" frameWidth="79" frameHeight="86"/>
	<SubTexture name="HogLeft0009" x="289.25" y="356.5" width="73.75" height="85.5" frameX="-5.25" frameY="-0.5" frameWidth="79" frameHeight="86"/>
	<SubTexture name="HogRight0000" x="436.5" y="356.5" width="101.5" height="86.25" frameX="-2.5" frameY="0" frameWidth="104" frameHeight="86.25"/>
	<SubTexture name="HogRight0001" x="538" y="356.5" width="100.5" height="85.25" frameX="-1.25" frameY="-1" frameWidth="104" frameHeight="86.25"/>
	<SubTexture name="HogRight0002" x="638.5" y="356.5" width="97.5" height="84.5" frameX="-0.25" frameY="-1.75" frameWidth="104" frameHeight="86.25"/>
	<SubTexture name="HogRight0003" x="736" y="356.5" width="97" height="84.25" frameX="0" frameY="-2" frameWidth="104" frameHeight="86.25"/>
	<SubTexture name="HogRight0004" x="833" y="356.5" width="97" height="84.25" frameX="0" frameY="-2" frameWidth="104" frameHeight="86.25"/>
	<SubTexture name="HogRight0005" x="736" y="356.5" width="97" height="84.25" frameX="0" frameY="-2" frameWidth="104" frameHeight="86.25"/>
	<SubTexture name="HogRight0006" x="833" y="356.5" width="97" height="84.25" frameX="0" frameY="-2" frameWidth="104" frameHeight="86.25"/>
	<SubTexture name="HogRight0007" x="736" y="356.5" width="97" height="84.25" frameX="0" frameY="-2" frameWidth="104" frameHeight="86.25"/>
	<SubTexture name="HogRight0008" x="833" y="356.5" width="97" height="84.25" frameX="0" frameY="-2" frameWidth="104" frameHeight="86.25"/>
	<SubTexture name="HogRight0009" x="736" y="356.5" width="97" height="84.25" frameX="0" frameY="-2" frameWidth="104" frameHeight="86.25"/>
	<SubTexture name="HogUp0000" x="930" y="356.5" width="80" height="105.5" frameX="0" frameY="0" frameWidth="80.5" frameHeight="105.5"/>
	<SubTexture name="HogUp0001" x="0" y="462" width="79.25" height="102.5" frameX="-0.5" frameY="-3" frameWidth="80.5" frameHeight="105.5"/>
	<SubTexture name="HogUp0002" x="79.25" y="462" width="77.25" height="97.5" frameX="-3.25" frameY="-7.75" frameWidth="80.5" frameHeight="105.5"/>
	<SubTexture name="HogUp0003" x="156.5" y="462" width="76.75" height="95.5" frameX="-3.75" frameY="-9.75" frameWidth="80.5" frameHeight="105.5"/>
	<SubTexture name="HogUp0004" x="233.25" y="462" width="76.75" height="95.5" frameX="-3.75" frameY="-9.75" frameWidth="80.5" frameHeight="105.5"/>
	<SubTexture name="HogUp0005" x="156.5" y="462" width="76.75" height="95.5" frameX="-3.75" frameY="-9.75" frameWidth="80.5" frameHeight="105.5"/>
	<SubTexture name="HogUp0006" x="233.25" y="462" width="76.75" height="95.5" frameX="-3.75" frameY="-9.75" frameWidth="80.5" frameHeight="105.5"/>
	<SubTexture name="HogUp0007" x="156.5" y="462" width="76.75" height="95.5" frameX="-3.75" frameY="-9.75" frameWidth="80.5" frameHeight="105.5"/>
	<SubTexture name="HogUp0008" x="233.25" y="462" width="76.75" height="95.5" frameX="-3.75" frameY="-9.75" frameWidth="80.5" frameHeight="105.5"/>
	<SubTexture name="HogUp0009" x="156.5" y="462" width="76.75" height="95.5" frameX="-3.75" frameY="-9.75" frameWidth="80.5" frameHeight="105.5"/>
</TextureAtlas>
