<?xml version="0.5" encoding="utf-8"?>
<TextureAtlas imagePath="tiny-bf.png">
	<!-- Made with CSS sprites, Fuck you animate :imp: -->

    <!-- Normal Animations -->

	<SubTexture name="Down0000" x="5" y="5" width="15" height="21.5"/>
	<SubTexture name="Down0001" x="30" y="5" width="15" height="21.5"/>

	<SubTexture name="Idle0000" x="55" y="5" width="15" height="21.5"/>
	<SubTexture name="Idle0001" x="5" y="36.5" width="15" height="21.5"/>
	<SubTexture name="Idle0002" x="30" y="36.5" width="15" height="21.5"/>
	<SubTexture name="Idle0003" x="55" y="36.5" width="15" height="21.5"/>
	<SubTexture name="Idle0004" x="80" y="5" width="15" height="21.5"/>

	<SubTexture name="Left0000" x="80" y="36.5" width="15" height="21.5"/>
	<SubTexture name="Left0001" x="5" y="68" width="15" height="21.5"/>

	<SubTexture name="Right0000" x="130" y="68" width="15" height="21.5"/>
	<SubTexture name="Right0001" x="5" y="99.5" width="15" height="21.5"/>

	<SubTexture name="Up0000" x="30" y="99.5" width="15" height="21.5"/>
	<SubTexture name="Up0001" x="55" y="99.5" width="15" height="21.5"/>

    <!-- Miss Animations -->

	<SubTexture name="MDown0000" x="5" y="5" width="15" height="21.5"/>
    <SubTexture name="MDown0001" x="30" y="5" width="15" height="21.5"/>
	<SubTexture name="MDown0002" x="30" y="5" width="15" height="21.5"/>
    <SubTexture name="MDown0003" x="55" y="5" width="15" height="21.5"/>
	<SubTexture name="MDown0004" x="55" y="5" width="15" height="21.5"/>
	<SubTexture name="MDown0005" x="55" y="5" width="15" height="21.5"/>
	<SubTexture name="MDown0006" x="55" y="5" width="15" height="21.5"/>
	<SubTexture name="MDown0007" x="55" y="5" width="15" height="21.5"/>
	<SubTexture name="MDown0008" x="55" y="5" width="15" height="21.5"/>
	<SubTexture name="MDown0009" x="55" y="5" width="15" height="21.5"/>
	<SubTexture name="MDown0010" x="55" y="5" width="15" height="21.5"/>
	<SubTexture name="MDown0011" x="55" y="5" width="15" height="21.5"/>
	<SubTexture name="MDown0012" x="55" y="5" width="15" height="21.5"/>

    <SubTexture name="MLeft0000" x="80" y="36.5" width="15" height="21.5"/>
    <SubTexture name="MLeft0001" x="80" y="68" width="15" height="21.5"/>
	<SubTexture name="MLeft0002" x="80" y="68" width="15" height="21.5"/>
    <SubTexture name="MLeft0003" x="105" y="5" width="15" height="21.5"/>
	<SubTexture name="MLeft0004" x="105" y="5" width="15" height="21.5"/>
	<SubTexture name="MLeft0005" x="105" y="5" width="15" height="21.5"/>
	<SubTexture name="MLeft0006" x="105" y="5" width="15" height="21.5"/>
	<SubTexture name="MLeft0007" x="105" y="5" width="15" height="21.5"/>
	<SubTexture name="MLeft0008" x="105" y="5" width="15" height="21.5"/>
	<SubTexture name="MLeft0009" x="105" y="5" width="15" height="21.5"/>
	<SubTexture name="MLeft0010" x="105" y="5" width="15" height="21.5"/>
	<SubTexture name="MLeft0011" x="105" y="5" width="15" height="21.5"/>
	<SubTexture name="MLeft0012" x="105" y="5" width="15" height="21.5"/>

    <SubTexture name="MRight0000" x="130" y="68" width="15" height="21.5"/>
    <SubTexture name="MRight0001" x="105" y="36.5" width="15" height="21.5"/>
	<SubTexture name="MRight0002" x="105" y="36.5" width="15" height="21.5"/>
    <SubTexture name="MRight0003" x="105" y="68" width="15" height="21.5"/>
	<SubTexture name="MRight0004" x="105" y="68" width="15" height="21.5"/>
	<SubTexture name="MRight0005" x="105" y="68" width="15" height="21.5"/>
	<SubTexture name="MRight0006" x="105" y="68" width="15" height="21.5"/>
	<SubTexture name="MRight0007" x="105" y="68" width="15" height="21.5"/>
	<SubTexture name="MRight0008" x="105" y="68" width="15" height="21.5"/>
	<SubTexture name="MRight0009" x="105" y="68" width="15" height="21.5"/>
	<SubTexture name="MRight0010" x="105" y="68" width="15" height="21.5"/>
	<SubTexture name="MRight0011" x="105" y="68" width="15" height="21.5"/>
	<SubTexture name="MRight0012" x="105" y="68" width="15" height="21.5"/>

    <SubTexture name="MUp0000" x="30" y="99.5" width="15" height="21.5"/>
    <SubTexture name="MUp0001" x="130" y="5" width="15" height="21.5"/>
	<SubTexture name="MUp0002" x="130" y="5" width="15" height="21.5"/>
    <SubTexture name="MUp0003" x="130" y="36.5" width="15" height="21.5"/>
	<SubTexture name="MUp0004" x="130" y="36.5" width="15" height="21.5"/>
	<SubTexture name="MUp0005" x="130" y="36.5" width="15" height="21.5"/>
	<SubTexture name="MUp0006" x="130" y="36.5" width="15" height="21.5"/>
	<SubTexture name="MUp0007" x="130" y="36.5" width="15" height="21.5"/>
	<SubTexture name="MUp0008" x="130" y="36.5" width="15" height="21.5"/>
	<SubTexture name="MUp0009" x="130" y="36.5" width="15" height="21.5"/>
	<SubTexture name="MUp0010" x="130" y="36.5" width="15" height="21.5"/>
	<SubTexture name="MUp0011" x="130" y="36.5" width="15" height="21.5"/>
	<SubTexture name="MUp0012" x="130" y="36.5" width="15" height="21.5"/>
</TextureAtlas>